pycrunchbase/__init__.py
pycrunchbase/pycrunchbase.py
pycrunchbase/resource/__init__.py
pycrunchbase/resource/acquisition.py
pycrunchbase/resource/address.py
pycrunchbase/resource/category.py
pycrunchbase/resource/degree.py
pycrunchbase/resource/fund.py
pycrunchbase/resource/fundinground.py
pycrunchbase/resource/image.py
pycrunchbase/resource/investment.py
pycrunchbase/resource/ipo.py
pycrunchbase/resource/job.py
pycrunchbase/resource/location.py
pycrunchbase/resource/news.py
pycrunchbase/resource/node.py
pycrunchbase/resource/organization.py
pycrunchbase/resource/page.py
pycrunchbase/resource/pageitem.py
pycrunchbase/resource/person.py
pycrunchbase/resource/product.py
pycrunchbase/resource/relationship.py
pycrunchbase/resource/stockexchange.py
pycrunchbase/resource/utils.py
pycrunchbase/resource/video.py
pycrunchbase/resource/website.py
pycrunchbase-0.3.9.dist-info/AUTHORS.rst
pycrunchbase-0.3.9.dist-info/LICENSE
pycrunchbase-0.3.9.dist-info/METADATA
pycrunchbase-0.3.9.dist-info/WHEEL
pycrunchbase-0.3.9.dist-info/top_level.txt
pycrunchbase-0.3.9.dist-info/RECORD
