Metadata-Version: 2.1
Name: pycrunchbase
Version: 0.3.9
Summary: Python bindings to CrunchBase
Home-page: https://github.com/ngzhian/pycrunchbase
Author: Ng Zhi An
Author-email: ngzhian@gmail.com
License: MIT
Keywords: crunchbase
Platform: UNKNOWN
Classifier: Development Status :: 4 - Beta
Classifier: Intended Audience :: Developers
Classifier: License :: OSI Approved :: MIT License
Classifier: Operating System :: Unix
Classifier: Operating System :: POSIX
Classifier: Operating System :: Microsoft :: Windows
Classifier: Programming Language :: Python
Classifier: Programming Language :: Python :: 2.7
Classifier: Programming Language :: Python :: 3.4
Classifier: Programming Language :: Python :: Implementation :: CPython
Classifier: Topic :: Utilities
Requires-Dist: requests (>=2.20.0)
Requires-Dist: six (>=1.9.0)
